TIMESERIESANALYSIS24/__init__.py
TIMESERIESANALYSIS24/gui.py
TIMESERIESANALYSIS24/smoothing.py
TIMESERIESANALYSIS24/stationarity.py
TIMESERIESANALYSIS24-0.1.dist-info/METADATA
TIMESERIESANALYSIS24-0.1.dist-info/WHEEL
TIMESERIESANALYSIS24-0.1.dist-info/top_level.txt
TIMESERIESANALYSIS24-0.1.dist-info/RECORD
