Metadata-Version: 2.1
Name: TIMESERIESANALYSIS24
Version: 0.1
Summary: timeseries analysis
Author: maria11
Author-email: mariapetrenko003@example.com
License: MIT
Requires-Dist: numpy
Requires-Dist: pandas
Requires-Dist: matplotlib
Requires-Dist: statsmodels
